photogallery/__init__.py
photogallery/admin.py
photogallery/apps.py
photogallery/models.py
photogallery/tests.py
photogallery/urls.py
photogallery/views.py
photogallery/migrations/0001_initial.py
photogallery/migrations/0002_auto_20200918_1520.py
photogallery/migrations/0003_picturepost_source.py
photogallery/migrations/0004_auto_20200923_1131.py
photogallery/migrations/0005_auto_20200923_1630.py
photogallery/migrations/0006_auto_20200923_1635.py
photogallery/migrations/0007_auto_20201011_1421.py
photogallery/migrations/__init__.py
photogallery/static/photogallery/detail.css
photogallery/static/photogallery/index.css
photogallery/templates/photogallery/detail.html
photogallery/templates/photogallery/index.html
django_photogallery-0.3.0.dist-info/LICENSE
django_photogallery-0.3.0.dist-info/METADATA
django_photogallery-0.3.0.dist-info/WHEEL
django_photogallery-0.3.0.dist-info/top_level.txt
django_photogallery-0.3.0.dist-info/RECORD
